{"coord": {"lon": -46.6361, "lat": -23.5475}, "weather": [{"id": 500, "main": "Rain", "description": "light rain", "icon": "10n"}], "base": "stations", "main": {"temp": 23.46, "feels_like": 24.13, "temp_min": 22.94, "temp_max": 23.94, "pressure": 1015, "humidity": 87, "sea_level": 1015, "grnd_level": 924}, "visibility": 10000, "wind": {"speed": 3.09, "deg": 170}, "rain": {"1h": 0.12}, "clouds": {"all": 75}, "dt": 1771463322, "sys": {"type": 2, "id": 2082654, "country": "BR", "sunrise": 1771404982, "sunset": 1771451093}, "timezone": -10800, "id": 3448439, "name": "S\u00e3o Paulo", "cod": 200}